pytest_repeated/__init__.py
pytest_repeated/plugin.py
pytest_repeated-0.3.9.dist-info/licenses/LICENSE
pytest_repeated-0.3.9.dist-info/METADATA
pytest_repeated-0.3.9.dist-info/WHEEL
pytest_repeated-0.3.9.dist-info/entry_points.txt
pytest_repeated-0.3.9.dist-info/top_level.txt
pytest_repeated-0.3.9.dist-info/RECORD
