Metadata-Version: 2.4
Name: pytest_repeated
Version: 0.3.9
Summary: A pytest module for very basic statistical tests. Repeat test multiple times and pass if the underlying test passes a threshold.
Author-email: Sinan Ozel <coding@sinan.slmail.me>
License: MIT License
Project-URL: Homepage, https://github.com/sinan-ozel/pytest-repeated
Project-URL: Issues, https://github.com/sinan-ozel/pytest-repeated/issues
Classifier: Programming Language :: Python :: 3
Classifier: License :: OSI Approved :: MIT License
Classifier: Operating System :: OS Independent
Classifier: Framework :: Pytest
License-File: LICENSE
Requires-Dist: pytest>=7.0.0
Requires-Dist: mpmath>=1.3.0
Provides-Extra: test
Requires-Dist: pytest>=7.0.0; extra == "test"
Requires-Dist: pytest-cov>=3.0.0; extra == "test"
Requires-Dist: pytest-depends>=1.0.1; extra == "test"
Requires-Dist: pytest-mock>=3.14.0; extra == "test"
Requires-Dist: httpx>=0.28.1; extra == "test"
Provides-Extra: dev
Requires-Dist: isort>=5.12.0; extra == "dev"
Requires-Dist: ruff>=0.12.11; extra == "dev"
Requires-Dist: black>=24.0.0; extra == "dev"
Requires-Dist: docformatter>=1.7.5; extra == "dev"
Provides-Extra: docs
Requires-Dist: mkdocs-material>=9.0.0; extra == "docs"
Requires-Dist: mkdocstrings[python]>=0.24.0; extra == "docs"
Provides-Extra: publish
Requires-Dist: packaging>=25.0; extra == "publish"
Dynamic: license-file
